assamtest/__init__.py
assamtest/__main__.py
assamtest/decorators.py
assamtest/expect.py
assamtest/register.py
assamtest/reporter.py
assamtest/runner.py
assamtest-0.0.1.dist-info/METADATA
assamtest-0.0.1.dist-info/RECORD
assamtest-0.0.1.dist-info/WHEEL
assamtest-0.0.1.dist-info/entry_points.txt
assamtest-0.0.1.dist-info/top_level.txt
